pyairfoil/__init__.py
pyairfoil/cli.py
pyairfoil/pyairfoil.py
pyairfoil-0.1.1.dist-info/AUTHORS.rst
pyairfoil-0.1.1.dist-info/LICENSE
pyairfoil-0.1.1.dist-info/METADATA
pyairfoil-0.1.1.dist-info/WHEEL
pyairfoil-0.1.1.dist-info/entry_points.txt
pyairfoil-0.1.1.dist-info/top_level.txt
pyairfoil-0.1.1.dist-info/RECORD
