Metadata-Version: 2.1
Name: pyairfoil
Version: 0.1.1
Summary: PyAirfoil contains methods and objects related to generating airfoil geometries
Home-page: https://github.com/rogersjw/pyairfoil
Author: Jonathan Rogers
Author-email: jonathan.w.rogers@gmail.com
License: MIT license
Keywords: pyairfoil
Platform: UNKNOWN
Classifier: Development Status :: 2 - Pre-Alpha
Classifier: Intended Audience :: Developers
Classifier: License :: OSI Approved :: MIT License
Classifier: Natural Language :: English
Classifier: Programming Language :: Python :: 2
Classifier: Programming Language :: Python :: 2.7
Classifier: Programming Language :: Python :: 3
Classifier: Programming Language :: Python :: 3.4
Classifier: Programming Language :: Python :: 3.5
Classifier: Programming Language :: Python :: 3.6
Classifier: Programming Language :: Python :: 3.7
Requires-Dist: Click (>=6.0)
